nn_torch/__init__.py
nn_torch/common/__init__.py
nn_torch/common/_types.py
nn_torch/cv/__init__.py
nn_torch/cv/dataset/__init__.py
nn_torch/cv/dataset/dataset.py
nn_torch/cv/models/__init__.py
nn_torch/cv/models/fpn.py
nn_torch/cv/models/mobilenet.py
nn_torch/cv/models/resnet.py
nn_torch/cv/models/detection/__init__.py
nn_torch/cv/models/detection/anchors.py
nn_torch-0.0.11.dist-info/LICENSE
nn_torch-0.0.11.dist-info/METADATA
nn_torch-0.0.11.dist-info/WHEEL
nn_torch-0.0.11.dist-info/top_level.txt
nn_torch-0.0.11.dist-info/RECORD
