Metadata-Version: 2.1
Name: nn-torch
Version: 0.0.11
Summary: neural networks implemented by pytorch
Home-page: UNKNOWN
Author: UNKNOWN
Author-email: UNKNOWN
License: UNKNOWN
Keywords: pip,pytorch,neural network,deep learning
Platform: any
Requires-Dist: torch
Requires-Dist: torchvision
Requires-Dist: pillow
Requires-Dist: numpy
